[
  {
    "arguments": [
      "/usr/bin/cc",
      "-c",
      "-Ideps",
      "-Isrc",
      "-Ibuild",
      "-x",
      "objective-c",
      "-DSOKOL_METAL",
      "-fobjc-arc",
      "-framework",
      "Metal",
      "-framework",
      "Cocoa",
      "-framework",
      "MetalKit",
      "-framework",
      "Quartz",
      "-o",
      "build/fwp",
      "src/draw.c"
    ],
    "directory": "/Users/george/git/fun-with-triangles",
    "file": "/Users/george/git/fun-with-triangles/src/draw.c",
    "output": "/Users/george/git/fun-with-triangles/build/fwp"
  },
  {
    "arguments": [
      "/usr/bin/cc",
      "-c",
      "-Ideps",
      "-Isrc",
      "-Ibuild",
      "-x",
      "objective-c",
      "-DSOKOL_METAL",
      "-fobjc-arc",
      "-framework",
      "Metal",
      "-framework",
      "Cocoa",
      "-framework",
      "MetalKit",
      "-framework",
      "Quartz",
      "-o",
      "build/fwp",
      "src/fwt.c"
    ],
    "directory": "/Users/george/git/fun-with-triangles",
    "file": "/Users/george/git/fun-with-triangles/src/fwt.c",
    "output": "/Users/george/git/fun-with-triangles/build/fwp"
  },
  {
    "arguments": [
      "/usr/bin/cc",
      "-c",
      "-Ideps",
      "-Isrc",
      "-Ibuild",
      "-x",
      "objective-c",
      "-DSOKOL_METAL",
      "-fobjc-arc",
      "-framework",
      "Metal",
      "-framework",
      "Cocoa",
      "-framework",
      "MetalKit",
      "-framework",
      "Quartz",
      "-o",
      "build/fwp",
      "src/input.c"
    ],
    "directory": "/Users/george/git/fun-with-triangles",
    "file": "/Users/george/git/fun-with-triangles/src/input.c",
    "output": "/Users/george/git/fun-with-triangles/build/fwp"
  },
  {
    "arguments": [
      "/usr/bin/cc",
      "-c",
      "-Ideps",
      "-Isrc",
      "-Ibuild",
      "-x",
      "objective-c",
      "-DSOKOL_METAL",
      "-fobjc-arc",
      "-framework",
      "Metal",
      "-framework",
      "Cocoa",
      "-framework",
      "MetalKit",
      "-framework",
      "Quartz",
      "-o",
      "build/fwp",
      "src/vfs.c"
    ],
    "directory": "/Users/george/git/fun-with-triangles",
    "file": "/Users/george/git/fun-with-triangles/src/vfs.c",
    "output": "/Users/george/git/fun-with-triangles/build/fwp"
  }
]
